numeth/__init__.py
numeth/differentiation.py
numeth/integration.py
numeth/interpolation.py
numeth/linear_algebra.py
numeth/optimization.py
numeth/root_finding.py
numeth-0.1.5.dist-info/licenses/LICENSE
numeth-0.1.5.dist-info/METADATA
numeth-0.1.5.dist-info/WHEEL
numeth-0.1.5.dist-info/top_level.txt
numeth-0.1.5.dist-info/RECORD
