Metadata-Version: 2.4
Name: numeth
Version: 0.1.5
Summary: A set of core numerical methods used in engineering and applied mathematics
Author-email: Abhisumat Kundu <kunduabhisumat@gmail.com>
License: MIT License
Project-URL: Repository, https://github.com/AbhisumatK/numeth-Numerical-Methods-Library
Keywords: numerical methods,scientific computing,engineering,applied mathematics,numerical,numeric
Classifier: Programming Language :: Python :: 3
Classifier: License :: OSI Approved :: MIT License
Classifier: Operating System :: OS Independent
Requires-Python: >=3.8
License-File: LICENSE
Requires-Dist: numpy
Dynamic: license-file
